Metadata-Version: 2.1
Name: Gistats
Version: 2.0.1
Summary:  Generate nice Statistics in your gists.
Home-page: https://github.com/ZSendokame/Gistats
Author: ZSendokame
License: MIT license
Platform: UNKNOWN
License-File: LICENSE
